{
  "meta": {
    "familia": "fp",
    "cicle_formatiu": "EVA",
    "titol_cicle": "Electromecanica de Vehicles Automobils",
    "familia_professional": "Transport i Manteniment de Vehicles",
    "grau": "mitja",
    "rd_titol": "RD 453/2010",
    "decret": "175/2022",
    "versio_schema": "1.0",
    "descripcio": "El mòdul de Motors Termics i Sistemes Auxiliars del cicle Electromecanica de Vehicles Automobils forma el tècnic en les competències professionals específiques d'aquesta àrea dins del sector de transport i manteniment de vehicles. Desenvolupa els coneixements tècnics, les habilitats pràctiques i les actituds professionals necessàries per exercir amb solvència les funcions associades a motors termics i sistemes auxiliars en empreses i institucions del sector. Les competències adquirides s'apliquen tant en el treball per compte aliè com en l'exercici lliure de la professió.\n\nEls continguts cobreixen els fonaments teòrics i els procediments tècnics de motors termics i sistemes auxiliars: la terminologia professional específica, els protocols i les normatives vigents del sector, les tècniques i instruments propis de l'àmbit, la documentació tècnica associada i els criteris de qualitat i seguretat aplicables. S'inclouen els aspectes ètics i deontològics de la professió, la normativa de prevenció de riscos laborals específica i la gestió dels recursos materials i humans implicats en les tasques del mòdul.\n\nLa metodologia combina les sessions teòriques amb la pràctica intensiva en tallers, laboratoris o espais professionals simulats del centre educatiu. L'alumne resol casos pràctics reals o simulats, elabora documentació tècnica i treballa en equip seguint els protocols professionals del sector de transport i manteniment de vehicles. L'avaluació integra proves teòriques, pràctiques de taller o laboratori, l'elaboració de documentació tècnica i l'observació de les actituds professionals durant les activitats pràctiques."
  },
  "modul": {
    "codi": "MP01",
    "nom": "Motors Termics i Sistemes Auxiliars",
    "hores_totals": 198,
    "uf": [
      {
        "codi": "UF1",
        "nom": "Motors de gasolina",
        "hores": 66,
        "resultats_aprenentatge": [
          {
            "codi": "RA1",
            "text": "Realitza el manteniment i reparacio de motors de gasolina.",
            "criteris_avaluacio": [
              {
                "codi": "CA1.1",
                "text": "Identifica components i funcionament del motor de gasolina.",
                "pes_percentual": 25
              },
              {
                "codi": "CA1.2",
                "text": "Diagnostica avaries en sistemes d'alimentacio i encesa.",
                "pes_percentual": 30
              },
              {
                "codi": "CA1.3",
                "text": "Realitza operacions de manteniment i reparacio del motor.",
                "pes_percentual": 25
              },
              {
                "codi": "CA1.4",
                "text": "Verifica parametres de funcionament amb equips de diagnosi.",
                "pes_percentual": 20
              }
            ]
          }
        ]
      },
      {
        "codi": "UF2",
        "nom": "Motors diesel",
        "hores": 66,
        "resultats_aprenentatge": [
          {
            "codi": "RA1",
            "text": "Realitza el manteniment i reparacio de motors diesel.",
            "criteris_avaluacio": [
              {
                "codi": "CA1.1",
                "text": "Identifica components especifics del motor diesel.",
                "pes_percentual": 25
              },
              {
                "codi": "CA1.2",
                "text": "Diagnostica avaries en sistemes d'injeccio diesel.",
                "pes_percentual": 30
              },
              {
                "codi": "CA1.3",
                "text": "Repara i ajusta sistemes common rail.",
                "pes_percentual": 25
              },
              {
                "codi": "CA1.4",
                "text": "Verifica emissions i sistemes anticontaminacio.",
                "pes_percentual": 20
              }
            ]
          }
        ]
      },
      {
        "codi": "UF3",
        "nom": "Sistemes auxiliars del motor",
        "hores": 66,
        "resultats_aprenentatge": [
          {
            "codi": "RA1",
            "text": "Mante i repara els sistemes auxiliars del motor.",
            "criteris_avaluacio": [
              {
                "codi": "CA1.1",
                "text": "Realitza manteniment del sistema de refrigeracio.",
                "pes_percentual": 25
              },
              {
                "codi": "CA1.2",
                "text": "Diagnostica i repara el sistema de lubrificacio.",
                "pes_percentual": 25
              },
              {
                "codi": "CA1.3",
                "text": "Mante el sistema d'escapament i catalitzadors.",
                "pes_percentual": 25
              },
              {
                "codi": "CA1.4",
                "text": "Verifica i repara el sistema de sobrealimentacio.",
                "pes_percentual": 25
              }
            ]
          }
        ]
      }
    ]
  }
}