{
  "meta": {
    "familia": "fp",
    "cicle_formatiu": "GA",
    "titol_cicle": "Gestió Administrativa",
    "grau": "mitja",
    "familia_professional": "Administració i Gestió",
    "font_tipus": "decret",
    "font_ref": "Decret 159/2015, de 14 de juliol",
    "titol_decret": "DECRET 159/2015, de 14 de juliol, pel qual s'estableix el currículum del cicle formatiu de grau mitjà de gestió administrativa.",
    "data_decret": "2015-07-14",
    "eli_url": "https://portaljuridic.gencat.cat/eli/es-ct/d/2015/07/14/159/dof/cat/xml",
    "rd_titol": "",
    "font": "XML AkomaNtoso - Portal DOGC (Diari Oficial de la Generalitat de Catalunya)",
    "versio_schema": "2.0",
    "metode_extraccio": "genera_fp_dogc.py (mecànic) — 0 IA generativa"
  },
  "modul": {
    "codi": "MP01",
    "nom": "comunicació empresarial i atenció al client",
    "hores_totals": 165,
    "uf": [
      {
        "codi": "UF1",
        "nom": "comunicació empresarial oral",
        "hores": 33,
        "resultats_aprenentatge": [
          {
            "codi": "RA1",
            "text": "Selecciona tècniques de comunicació, relacionant-les amb l’estructura i la imatge corporativa de l’empresa o organització i els fluxos d’informació existents.",
            "criteris_avaluacio": [
              {
                "codi": "CA11",
                "text": "Reconeix la necessitat de comunicació entre les persones en l’àmbit empresarial i/o de les organitzacions."
              },
              {
                "codi": "CA12",
                "text": "Distingeix entre comunicació i informació en situacions empresarials i/o corporatives."
              },
              {
                "codi": "CA13",
                "text": "Distingeix els elements i processos que intervenen en la comunicació oral."
              },
              {
                "codi": "CA14",
                "text": "Reconeix els obstacles que hi pot haver en un procés de comunicació oral, presencial o no presencial."
              },
              {
                "codi": "CA15",
                "text": "Determina la millor forma i actitud a l’hora de presentar el missatge oral."
              },
              {
                "codi": "CA16",
                "text": "Aplica els conceptes d’imatge i cultura de l’empresa a l’àmbit de la comunicació oral."
              },
              {
                "codi": "CA17",
                "text": "Diferencia els tipus d’organitzacions i el seu organigrama funcional."
              },
              {
                "codi": "CA18",
                "text": "Distingeix les comunicacions orals, internes i externes, i els fluxos d’informació dins de l’empresa."
              },
              {
                "codi": "CA19",
                "text": "Selecciona el destinatari i el canal adequat per a cada situació pel que fa a la comunicació oral."
              }
            ],
            "continguts": []
          },
          {
            "codi": "RA2",
            "text": "Transmet informació de forma oral, vinculant-la als usos i costums socioprofessionals habituals en l’empresa i/o organització.",
            "criteris_avaluacio": [
              {
                "codi": "CA21",
                "text": "Identifica els principis bàsics a tenir en compte en la comunicació verbal."
              },
              {
                "codi": "CA22",
                "text": "Identifica el protocol de comunicació verbal i no verbal en les comunicacions presencials i no presencials."
              },
              {
                "codi": "CA23",
                "text": "Utilitza amb eficàcia les dues llengües oficials en la transmissió d’informació i comunicació orals."
              },
              {
                "codi": "CA24",
                "text": "Té en compte els costums socioculturals, locals i els dels clients o usuaris, i els usos empresarials."
              },
              {
                "codi": "CA25",
                "text": "Identifica l’interlocutor, en situacions professionals habituals, observant les normes de protocol establertes i els principis deontològics de la professió, i adaptant la seva actitud i conversa."
              },
              {
                "codi": "CA26",
                "text": "Elabora el missatge verbal, de manera concreta i precisa, valorant-ne i minimitzant-ne les possibles dificultats en la transmissió."
              },
              {
                "codi": "CA27",
                "text": "Utilitza el lèxic, les expressions i les estructures adequats al tipus de comunicació i als interlocutors."
              },
              {
                "codi": "CA28",
                "text": "Aplica, segons els protocols establerts, el tractament personal i de gènere corresponents en situacions empresarials habituals."
              },
              {
                "codi": "CA29",
                "text": "Presenta el missatge verbal elaborat utilitzant-hi el llenguatge no verbal més adequat."
              },
              {
                "codi": "CA210",
                "text": "Utilitza equips de telefonia, fixa i mòbil, i equips informàtics aplicant-ne les normes bàsiques d’ús."
              },
              {
                "codi": "CA211",
                "text": "Valora si la informació és transmesa amb claredat, de forma estructurada, amb precisió, amb cortesia, amb respecte i sensibilitat."
              },
              {
                "codi": "CA212",
                "text": "Analitza els errors comesos i proposa les accions correctives necessàries."
              },
              {
                "codi": "CA213",
                "text": "Identifica les tècniques bàsiques utilitzades en els centres d’atenció al client/usuari i els protocols d’actuació establerts."
              },
              {
                "codi": "CA214",
                "text": "Utilitza amb autonomia la llengua anglesa en comunicacions orals bàsiques."
              }
            ],
            "continguts": [
              {
                "bloc": "Selecció de tècniques de comunicació empresarial oral",
                "items": [
                  "Elements i barreres de la comunicació oral.",
                  "Comunicació i informació orals i comportament.",
                  "Les relacions humanes i laborals en l’empresa.",
                  "L’organització empresarial. Organigrames.",
                  "Principis i tipus d’organització empresarial.",
                  "Departaments i àrees funcionals tipus.",
                  "Funcions del personal en l’organització.",
                  "Descripció dels fluxos de comunicació oral.",
                  "La comunicació oral interna en l’empresa: comunicació formal i informal.",
                  "La comunicació oral externa en l’empresa. Les relacions públiques."
                ]
              },
              {
                "bloc": "Transmissió de comunicació oral en l’empresa",
                "items": [
                  "Principis bàsics en les comunicacions orals.",
                  "Normes d’informació i atenció oral.",
                  "Tècniques de comunicació oral, habilitats socials i protocol.",
                  "La comunicació no verbal.",
                  "La comunicació verbal dins de l’àmbit de l’empresa i organitzacions.",
                  "La comunicació telefònica. Protocols empresarials en la gravació de missatges.",
                  "El telèfon i el seu ús. Telefonia fixa i telefonia mòbil: usos de cortesia. La centraleta. Ús de les guies telefòniques. Normes per parlar correctament per telèfon.",
                  "Les centrals de serveis d’atenció telefònica als clients/usuaris. Call centers.",
                  "La informàtica en les comunicacions verbals. Videoconferències: programaris i protocols d’actuació.",
                  "Comunicacions a la recepció de visites: acollida, identificació, gestió, comiat, en les dues llengües oficials i en llengua anglesa."
                ]
              }
            ]
          }
        ]
      },
      {
        "codi": "UF2",
        "nom": "comunicació empresarial escrita",
        "hores": 33,
        "resultats_aprenentatge": [
          {
            "codi": "RA1",
            "text": "Selecciona tècniques de comunicació escrita, relacionant-les amb l’estructura i imatge corporativa de l’empresa o organització i els fluxos d’informació existents.",
            "criteris_avaluacio": [
              {
                "codi": "CA11",
                "text": "Identifica i valora la conveniència i/o obligació de comunicació escrita entre les persones en l’àmbit empresarial i/o de les organitzacions."
              },
              {
                "codi": "CA12",
                "text": "Distingeix entre comunicació i informació en situacions empresarials i/o corporatives."
              },
              {
                "codi": "CA13",
                "text": "Distingeix els elements i processos que intervenen en la comunicació escrita segons els canals utilitzats."
              },
              {
                "codi": "CA14",
                "text": "Reconeix els obstacles que hi pot haver en els processos de comunicació escrita habituals de les empreses."
              },
              {
                "codi": "CA15",
                "text": "Determina la millor forma i actitud a l’hora de presentar el missatge escrit segons el canal utilitzat."
              },
              {
                "codi": "CA16",
                "text": "Aplica els conceptes d’imatge i cultura de l’empresa a l’àmbit de la comunicació escrita."
              },
              {
                "codi": "CA17",
                "text": "Distingeix les comunicacions escrites, internes i externes, i els fluxos d’informació dins de l’empresa."
              },
              {
                "codi": "CA18",
                "text": "Selecciona el destinatari i el canal adequat per a cada situació pel que fa a la comunicació escrita."
              }
            ],
            "continguts": []
          },
          {
            "codi": "RA2",
            "text": "Transmet informació escrita, aplicant les tècniques d'estil a diferents tipus de documents propis de l’empresa i de l'administració pública.",
            "criteris_avaluacio": [
              {
                "codi": "CA21",
                "text": "Selecciona els suports adequats en cada cas per elaborar i trametre els documents: tipus de paper, sobres i d’altres."
              },
              {
                "codi": "CA22",
                "text": "Identifica i reconeix els avantatges i els inconvenients dels canals de transmissió: correu convencional, correu electrònic, fax, burofax, missatges curts o altres similars."
              },
              {
                "codi": "CA23",
                "text": "Diferencia els suports més apropiats en funció dels criteris de rapidesa, seguretat, i confidencialitat."
              },
              {
                "codi": "CA24",
                "text": "Identifica el destinatari aplicant les normes de protocol i els principis deontològics establerts."
              },
              {
                "codi": "CA25",
                "text": "Aplica en tot tipus de comunicació escrita el tractament personal i de gènere adequat."
              },
              {
                "codi": "CA26",
                "text": "Utilitza els llibres i manuals d’estil de l’empresa o corporació en les dues llengües oficials i en llengua anglesa."
              },
              {
                "codi": "CA27",
                "text": "Classifica les tipologies més habituals de documents dins de l’empresa segons la seva finalitat."
              },
              {
                "codi": "CA28",
                "text": "Redacta, en les dues llengües oficials, els documents apropiats a les situacions professionals habituals, complint les normes ortogràfiques i sintàctiques en funció de la seva finalitat i de la situació de partida."
              },
              {
                "codi": "CA29",
                "text": "Identifica les eines de recerca d’informació per elaborar la documentació."
              },
              {
                "codi": "CA210",
                "text": "Utilitza amb agilitat aplicacions informàtiques de processament de textos o autoedició."
              },
              {
                "codi": "CA211",
                "text": "Utilitza els teclats aplicant correctament les tècniques mecanogràfiques de posició dels dits i corporal, amb velocitat, precisió i correcció de les dades gravades i/o els documents redactats."
              },
              {
                "codi": "CA212",
                "text": "Emplena els llibres de registre d’entrada i sortida de correspondència i paqueteria en suport informàtic i convencional."
              },
              {
                "codi": "CA213",
                "text": "Utilitza la normativa sobre protecció de dades, conservació i destrucció de documents establerts per a les empreses i institucions, públiques i privades."
              },
              {
                "codi": "CA214",
                "text": "Aplica, en l’àmbit de la documentació escrita, les tècniques de les tres erres: reduir, reutilitzar i reciclar."
              },
              {
                "codi": "CA215",
                "text": "Utilitza amb autonomia la llengua anglesa en comunicacions escrites bàsiques."
              }
            ],
            "continguts": [
              {
                "bloc": "Selecció de tècniques de comunicació empresarial escrita",
                "items": [
                  "Elements i barreres de la comunicació escrita.",
                  "Comunicació i informació escrita i comportament.",
                  "Les relacions humanes i laborals en l’empresa.",
                  "L’organització empresarial. Organigrames.",
                  "Principis i tipus d’organització empresarial.",
                  "Descripció dels fluxos de comunicació escrita.",
                  "Canals de comunicació escrita. Canals convencionals, noves tecnologies de telefonia i informàtiques. Internet, intranet, plataformes col·laboratives i de comunicació.",
                  "La comunicació interna en l’empresa: comunicació formal i informal.",
                  "La comunicació externa en l’empresa. La publicitat."
                ]
              },
              {
                "bloc": "Transmissió de comunicació escrita en l’empresa",
                "items": [
                  "La comunicació escrita en l’empresa en les dues llengües oficials i en llengua anglesa.",
                  "Normes de comunicació i expressió escrita.",
                  "Llibres i manuals d’estil de comunicació escrita en l’empresa i les organitzacions.",
                  "Característiques principals de la correspondència comercial.",
                  "La carta comercial. Estructura, estils i classes.",
                  "Formats tipus de documents d’ús en l’empresa i en les administracions públiques.",
                  "Mitjans i equips ofimàtics i telemàtics.",
                  "El correu electrònic i altres mitjans de comunicació en línia . Protocols de bones pràctiques en la comunicació professional en línia . Cibermaneres.",
                  "Les centrals de serveis d’atenció en línia als clients/usuaris.",
                  "La recepció, tramesa i registre de la correspondència.",
                  "Servei de correus, circulació interna de correspondència i paqueteria.",
                  "Aplicació de procediments de seguretat i confidencialitat de la informació."
                ]
              }
            ]
          }
        ]
      },
      {
        "codi": "UF3",
        "nom": "sistemes d’arxiu",
        "hores": 33,
        "resultats_aprenentatge": [
          {
            "codi": "RA1",
            "text": "Arxiva informació en suport paper i informàtic, reconeixent els criteris d’eficiència i estalvi en els tràmits administratius.",
            "criteris_avaluacio": [
              {
                "codi": "CA11",
                "text": "Identifica els avantatges i els inconvenients del sistema d’organització de la informació emprat i valora els objectius que persegueix l’empresa o organització."
              },
              {
                "codi": "CA12",
                "text": "Diferencia les tècniques d’organització de la informació que es poden aplicar en una empresa o institució, així com els procediments habituals de registre, classificació, distribució, arxiu i destrucció de la informació en les organitzacions."
              },
              {
                "codi": "CA13",
                "text": "Identifica els suports d’arxiu i registre i les prestacions de les aplicacions informàtiques específiques més utilitzades en funció de les característiques de la informació a emmagatzemar."
              },
              {
                "codi": "CA14",
                "text": "Determina, en situacions professionals habituals, el sistema d’accessos i els nivells de seguretat que han d’acomplir els arxius i registres en acompliment de la normativa vigent i segons els suports utilitzats."
              },
              {
                "codi": "CA15",
                "text": "Identifica les principals bases de dades de les organitzacions, l’estructura i les funcions."
              },
              {
                "codi": "CA16",
                "text": "Determina el sistema de classificació, registre i arxiu apropiats per al tipus de document."
              },
              {
                "codi": "CA17",
                "text": "Reconeix la documentació que han d’integrar els diferents expedients, arxius i registres, segons els criteris establerts per l’empresa o l’organització."
              },
              {
                "codi": "CA18",
                "text": "Confecciona, segons instruccions rebudes, arbres d’arxius informàtics per a una ordenació òptima de la documentació digital."
              },
              {
                "codi": "CA19",
                "text": "Confecciona registres informàtics senzills amb aplicacions informàtiques habituals que permetin recerques bàsiques."
              },
              {
                "codi": "CA110",
                "text": "Aplica les tècniques d'arxiu adequades en els intercanvis d’informació telemàtica (intranet, extranet, correu electrònic, plataformes col·laboratives o de comunicació i altres)."
              },
              {
                "codi": "CA111",
                "text": "Reconeix i utilitza amb agilitat els procediments de consulta, en suport convencional i digital, i de conservació de la informació i la documentació, i en detecta els errors."
              },
              {
                "codi": "CA112",
                "text": "Utilitza els teclats aplicant-hi correctament les tècniques mecanogràfiques de posició dels dits i de posició corporal, amb velocitat, precisió i correcció de les dades gravades, dels documents redactats i de les consultes efectuades."
              },
              {
                "codi": "CA113",
                "text": "Respecta els nivells de protecció, seguretat i accés a la informació, així com la normativa vigent tant en documents físics com en bases de dades informàtiques."
              },
              {
                "codi": "CA114",
                "text": "Aplica, en l’elaboració i arxiu de la documentació, les tècniques de les tres erres: reduir, reutilitzar i reciclar."
              },
              {
                "codi": "CA115",
                "text": "Reconeix els avantatges del “paper zero” i n’identifica les organitzacions pioneres, i els paràmetres de funcionament necessaris."
              }
            ],
            "continguts": [
              {
                "bloc": "Arxiu de la informació en suport paper i informàtic",
                "items": [
                  "Finalitats i objectius de l’arxiu i els registres.",
                  "Tècniques d’arxiu. Classes d’arxiu segons diferents paràmetres.",
                  "Confecció i presentació d’informes procedents de l’arxiu.",
                  "Purga i destrucció de la documentació.",
                  "Confidencialitat de la informació i documentació. Llei de protecció de dades.",
                  "Centralització o descentralització de l’arxiu.",
                  "Arxiu de la informació en suport paper.",
                  "Arxiu de la informació en suport informàtic."
                ]
              }
            ]
          }
        ]
      },
      {
        "codi": "UF4",
        "nom": "atenció al client/usuari",
        "hores": 33,
        "resultats_aprenentatge": [
          {
            "codi": "RA1",
            "text": "Reconeix necessitats de possibles clients aplicant tècniques de comunicació.",
            "criteris_avaluacio": [
              {
                "codi": "CA11",
                "text": "Desenvolupa tècniques de comunicació i habilitats socials que faciliten l’empatia amb el client/usuari en situacions d’atenció/assessorament."
              },
              {
                "codi": "CA12",
                "text": "Identifica les fases que componen el procés d’atenció al client/consumidor/usuari a través de diferents canals de comunicació."
              },
              {
                "codi": "CA13",
                "text": "Reconeix els errors més habituals que es cometen en la comunicació amb el client/consumidor/usuari, en petites i mitjanes empreses o en grans empreses i/o organitzacions."
              },
              {
                "codi": "CA14",
                "text": "Identifica el comportament del client/consumidor/usuari."
              },
              {
                "codi": "CA15",
                "text": "Analitza les motivacions de compra o demanda d’un servei del client/usuari."
              },
              {
                "codi": "CA16",
                "text": "Obté, en cas que sigui necessari, la informació històrica del client."
              },
              {
                "codi": "CA17",
                "text": "Adapta de manera adequada l’actitud i el discurs a la situació de la qual es parteix."
              },
              {
                "codi": "CA18",
                "text": "Manté la forma i l’actitud adequades en l’atenció i assessorament a un client/usuari en funció del canal de comunicació utilitzat."
              },
              {
                "codi": "CA19",
                "text": "Distingeix les diferents etapes d’un procés comunicatiu d’atenció al client."
              }
            ],
            "continguts": []
          },
          {
            "codi": "RA2",
            "text": "Atén consultes, queixes i reclamacions de possibles clients aplicant la normativa vigent en matèria de consum.",
            "criteris_avaluacio": [
              {
                "codi": "CA21",
                "text": "Descriu les funcions del departament d’atenció al client en empreses/usuaris en les organitzacions."
              },
              {
                "codi": "CA22",
                "text": "Interpreta la comunicació rebuda per part del client/usuari."
              },
              {
                "codi": "CA23",
                "text": "Identifica els elements de la queixa/reclamació."
              },
              {
                "codi": "CA24",
                "text": "Reconeix les fases que componen el pla intern de resolució de queixes/reclamacions i els circuits administratius corresponents."
              },
              {
                "codi": "CA25",
                "text": "Identifica i localitza la informació que cal subministrar al client/usuari en l’àmbit de les seves competències o segons les instruccions rebudes."
              },
              {
                "codi": "CA26",
                "text": "Utilitza els documents propis de la gestió de consultes, queixes i reclamacions, o les aplicacions o registres informàtics."
              },
              {
                "codi": "CA27",
                "text": "Emplena, en cas que sigui necessari, formularis i escrits de resposta, en les dues llengües oficials, segons les instruccions rebudes i respectant els protocols establerts, utilitzant mitjans electrònics o altres canals de comunicació."
              },
              {
                "codi": "CA28",
                "text": "Emplena formularis i/o escrits de resposta senzills, en llengua anglesa, sobre consultes i reclamacions bàsiques."
              },
              {
                "codi": "CA29",
                "text": "Reconeix la importància de la protecció del consumidor."
              },
              {
                "codi": "CA210",
                "text": "Identifica la normativa en matèria de consum."
              },
              {
                "codi": "CA211",
                "text": "Diferencia els tipus de demanda o reclamació."
              },
              {
                "codi": "CA212",
                "text": "Reconeix els organismes de defensa dels clients/consumidors/usuaris."
              }
            ],
            "continguts": []
          },
          {
            "codi": "RA3",
            "text": "Potencia la imatge d’empresa reconeixent i aplicant els elements i eines del màrqueting en el seu ampli ventall de possibilitats.",
            "criteris_avaluacio": [
              {
                "codi": "CA31",
                "text": "Identifica el concepte de màrqueting."
              },
              {
                "codi": "CA32",
                "text": "Reconeix les funcions principals del màrqueting, en les petites i mitjanes empreses i en les grans empreses i organitzacions."
              },
              {
                "codi": "CA33",
                "text": "Valora la importància del departament de màrqueting, en les petites i mitjanes empreses i en les grans empreses i organitzacions."
              },
              {
                "codi": "CA34",
                "text": "Diferencia els elements i eines bàsics que componen el màrqueting."
              },
              {
                "codi": "CA35",
                "text": "Reconeix la rellevància del màrqueting mòbil i el màrqueting digital i les seves potencialitats."
              },
              {
                "codi": "CA36",
                "text": "Valora la importància de la imatge corporativa per aconseguir els objectius de l’empresa."
              },
              {
                "codi": "CA37",
                "text": "Valora la importància de les relacions públiques i l’atenció al client per a la imatge de l’empresa."
              },
              {
                "codi": "CA38",
                "text": "Identifica la fidelització del client com a un objectiu prioritari del màrqueting, i reconeix els mitjans més utilitzats per aconseguir-la per empreses i corporacions."
              }
            ],
            "continguts": []
          },
          {
            "codi": "RA4",
            "text": "Aplica procediments de qualitat en l'atenció al client identificant-ne els estàndards establerts.",
            "criteris_avaluacio": [
              {
                "codi": "CA41",
                "text": "Identifica els factors que influeixen en la prestació del servei al client/usuari."
              },
              {
                "codi": "CA42",
                "text": "Descriu les fases del procediment de relació amb els clients/usuaris."
              },
              {
                "codi": "CA43",
                "text": "Descriu els estàndards de qualitat definits en la prestació del servei."
              },
              {
                "codi": "CA44",
                "text": "Valora la importància d’una actitud proactiva per anticipar-se a possibles incidències en els processos."
              },
              {
                "codi": "CA45",
                "text": "Reconeix l’impacte que una actitud d’orientació al client empàtica i un alt nivell de resiliència tenen en un servei d’atenció al client de qualitat."
              },
              {
                "codi": "CA46",
                "text": "Detecta els errors produïts en la prestació del servei i proposa millores en l’àmbit d’actuació."
              },
              {
                "codi": "CA47",
                "text": "Aplica el tractament adequat en la gestió de les anomalies produïdes."
              },
              {
                "codi": "CA48",
                "text": "Explica el significat i valora la importància del servei postvenda en els processos comercials."
              },
              {
                "codi": "CA49",
                "text": "Reconeix les garanties dels productes o serveis comercialitzats, i pot informar-ne al client en l’àmbit de les seves competències."
              },
              {
                "codi": "CA410",
                "text": "Descriu les variables que constitueixen el servei postvenda i la seva relació amb la fidelització del client."
              },
              {
                "codi": "CA411",
                "text": "Identifica les situacions comercials que requereixen seguiment i servei postvenda."
              },
              {
                "codi": "CA412",
                "text": "Descriu els mètodes més utilitzats habitualment en el control de qualitat del servei postvenda, així com les seves fases i eines."
              },
              {
                "codi": "CA413",
                "text": "Aplica, en l’àmbit de la seva competència, els controls de qualitat corresponents segons les instruccions rebudes."
              },
              {
                "codi": "CA414",
                "text": "Identifica les característiques de l’externalització de l’atenció al client/usuari, valorant-ne possibles avantatges i inconvenients."
              }
            ],
            "continguts": [
              {
                "bloc": "Reconeixement de necessitats dels clients",
                "items": [
                  "Concepte i identificació de client: el client intern; el client extern.",
                  "El coneixement del client/usuari i les seves motivacions.",
                  "Elements de l’atenció al client/usuari: entorn, organització i empleats.",
                  "Fases de l’atenció al client: l’acollida, el seguiment, la gestió i el comiat.",
                  "La percepció del client/usuari respecte a l’atenció rebuda.",
                  "La satisfacció del client.",
                  "Els processos en contacte amb el client extern.",
                  "Aplicacions específiques de gestió de clients."
                ]
              },
              {
                "bloc": "Atenció de consultes, queixes i reclamacions",
                "items": [
                  "El departament d’atenció al client/consumidor/usuari. Funcions.",
                  "Valoració del client de l’atenció rebuda: reclamació, queixa, suggeriment, felicitació.",
                  "Elements d’una queixa o reclamació.",
                  "Les fases de la resolució de queixes/reclamacions. Comunicacions de resposta en les dues llengües oficials i respostes bàsiques en llengua anglesa.",
                  "El consumidor.",
                  "Institucions de consum.",
                  "Normativa en matèria de consum.",
                  "Procediment de recollida de les reclamacions i denúncies.",
                  "Tramitació i gestió.",
                  "Institucions de defensa dels drets dels consumidors."
                ]
              },
              {
                "bloc": "Potenciació de la imatge de l’empresa",
                "items": [
                  "El màrqueting en l’activitat econòmica: la seva influència en la imatge de l'empresa i/o organització.",
                  "Naturalesa i abast del màrqueting.",
                  "Polítiques de comunicació.",
                  "El màrqueting mòbil. Les tecnologies de comunicació i telefonia mòbils. Georeferències.",
                  "El màrqueting digital. Les xarxes a internet com a eina de fidelització i promoció. Principals xarxes.",
                  "Xarxes socials. Xarxes professionals. Xarxes audiovisuals. La reputació en línia.",
                  "Aplicacions informàtiques específiques de màrqueting."
                ]
              },
              {
                "bloc": "Aplicació de procediments de qualitat en l’atenció al client",
                "items": [
                  "La qualitat del servei com a element de la competitivitat de l’empresa.",
                  "Les actituds i la gestió de les emocions en l’atenció al client.",
                  "Tractament d'anomalies produïdes en la prestació del servei.",
                  "Garanties.",
                  "Procediments de control del servei.",
                  "Avaluació i control del servei.",
                  "Control del servei postvenda.",
                  "La fidelització del client.",
                  "L’externalització dels centres d’atenció als clients/usuaris."
                ]
              }
            ]
          }
        ]
      }
    ]
  }
}